pytest_breakword/__init__.py
pytest_breakword/main.py
pytest_breakword/version.py
pytest_breakword-0.1.2.dist-info/entry_points.txt
pytest_breakword-0.1.2.dist-info/LICENSE
pytest_breakword-0.1.2.dist-info/WHEEL
pytest_breakword-0.1.2.dist-info/METADATA
pytest_breakword-0.1.2.dist-info/RECORD
