Metadata-Version: 2.1
Name: pytest-breakword
Version: 0.1.2
Summary: Use breakword with pytest
License: MIT
Author: Olivier Breuleux
Author-email: breuleux@gmail.com
Requires-Python: >=3.7,<4.0
Classifier: Framework :: Pytest
Classifier: License :: OSI Approved :: MIT License
Classifier: Programming Language :: Python :: 3
Classifier: Programming Language :: Python :: 3.7
Classifier: Programming Language :: Python :: 3.8
Classifier: Programming Language :: Python :: 3.9
Requires-Dist: breakword (>=0.3.1,<0.4.0)
Requires-Dist: pytest (>=6.2.4,<7.0.0)
